pyetherbalance/__init__.py
pyetherbalance/erc20tokens.py
pyetherbalance/pyetherbalance.py
pyetherbalance-0.0.1.dist-info/LICENSE
pyetherbalance-0.0.1.dist-info/METADATA
pyetherbalance-0.0.1.dist-info/WHEEL
pyetherbalance-0.0.1.dist-info/top_level.txt
pyetherbalance-0.0.1.dist-info/RECORD
