Metadata-Version: 2.1
Name: pyetherbalance
Version: 0.0.1
Summary: Lightweight Module to get Ethereum and ERC20 token balances
Home-page: http://github.com/araa47
Author: Akshay Ramasubramanian
Author-email: araa@connect.ust.hk
License: MIT
Keywords: ethereum
Platform: UNKNOWN
Classifier: Development Status :: 4 - Beta
Classifier: Environment :: Web Environment
Classifier: License :: OSI Approved :: MIT License
Classifier: Programming Language :: Python
Classifier: Programming Language :: Python :: 3.5
Classifier: Programming Language :: Python :: 3.6
Classifier: Programming Language :: Python :: 3.7
Classifier: Topic :: Internet
Classifier: Topic :: Software Development :: Libraries 
Classifier: Topic :: Software Development :: Libraries :: Python Modules
Requires-Dist: requests
